chsel/__init__.py
chsel/conversion.py
chsel/costs.py
chsel/initialization.py
chsel/measure.py
chsel/quality_diversity.py
chsel/registration_util.py
chsel/se2.py
chsel/sgd.py
chsel/types.py
chsel/wrapper.py
chsel-0.2.1.dist-info/LICENSE.txt
chsel-0.2.1.dist-info/METADATA
chsel-0.2.1.dist-info/WHEEL
chsel-0.2.1.dist-info/top_level.txt
chsel-0.2.1.dist-info/RECORD
