Metadata-Version: 2.1
Name: chsel
Version: 0.2.1
Summary: Constrained pose Hypothesis Set Elimination official code for pose estimation
Author-email: Sheng Zhong <zhsh@umich.edu>
Maintainer-email: Sheng Zhong <zhsh@umich.edu>
License: Copyright (c) 2023 University of Michigan ARM Lab
Project-URL: Homepage, https://github.com/UM-ARM-Lab/chsel
Project-URL: Bug Reports, https://github.com/UM-ARM-Lab/cshel/issues
Project-URL: Source, https://github.com/UM-ARM-Lab/chsel
Keywords: robotics,pose estimation,registration,pytorch
Classifier: Development Status :: 4 - Beta
Classifier: Intended Audience :: Developers
Classifier: License :: OSI Approved :: MIT License
Classifier: Programming Language :: Python :: 3
Classifier: Programming Language :: Python :: 3 :: Only
Requires-Python: >=3.8
License-File: LICENSE.txt
Requires-Dist: cma
Requires-Dist: torch
Requires-Dist: numpy
Requires-Dist: matplotlib
Requires-Dist: arm-pytorch-utilities
Requires-Dist: pytorch-kinematics
Requires-Dist: pytorch-volumetric
Requires-Dist: ribs[all]
Provides-Extra: test
Requires-Dist: pytest; extra == "test"
